PyPushBullet/__init__.py
PyPushBullet/client.py
PyPushBullet/logger.py
PyPushBullet-0.2.7.dist-info/LICENSE
PyPushBullet-0.2.7.dist-info/METADATA
PyPushBullet-0.2.7.dist-info/WHEEL
PyPushBullet-0.2.7.dist-info/top_level.txt
PyPushBullet-0.2.7.dist-info/RECORD
